davesci/__init__.py
davesci/__main__.py
davesci-0.0.1.dist-info/METADATA
davesci-0.0.1.dist-info/WHEEL
davesci-0.0.1.dist-info/top_level.txt
davesci-0.0.1.dist-info/RECORD
